mintlemon/__init__.py
mintlemon/data/TR_non_breaking_prefixes.txt
mintlemon/data/ascii_to_str_dict.pickle
mintlemon/data/stop_words.txt
mintlemon/normalizer/__init__.py
mintlemon/normalizer/_builtin.py
mintlemon/normalizer/normalizer.py
mintlemon/normalizer/text_to_root_dtm.py
mintlemon/sentence_splitter/__init__.py
mintlemon/sentence_splitter/sentence_splitter.py
mintlemon_turkish_nlp-0.3.2.dist-info/AUTHORS.rst
mintlemon_turkish_nlp-0.3.2.dist-info/LICENSE
mintlemon_turkish_nlp-0.3.2.dist-info/METADATA
mintlemon_turkish_nlp-0.3.2.dist-info/WHEEL
mintlemon_turkish_nlp-0.3.2.dist-info/top_level.txt
mintlemon_turkish_nlp-0.3.2.dist-info/RECORD
