Metadata-Version: 2.1
Name: mintlemon-turkish-nlp
Version: 0.3.2
Summary: Mint & Lemon Turkish NLP Library developed by Mint & Lemon Development Team.
Home-page: https://github.com/Teknofest-Nane-Limon/mintlemon-turkish-nlp
Author: Mint&Lemon
License: Apache License, Version 2.0
Project-URL: Tracker, https://github.com/Teknofest-Nane-Limon/mintlemon-turkish-nlp/issues
Project-URL: Documentation, https://mintlemon-turkish-nlp.readthedocs.io
Classifier: Development Status :: 2 - Pre-Alpha
Classifier: Intended Audience :: Developers
Classifier: Intended Audience :: Education
Classifier: Intended Audience :: Information Technology
Classifier: Intended Audience :: Science/Research
Classifier: Topic :: Text Processing
Classifier: Topic :: Software Development
Classifier: Topic :: Software Development :: Libraries
Classifier: Topic :: Scientific/Engineering :: Mathematics
Classifier: Topic :: Scientific/Engineering :: Artificial Intelligence
Classifier: Topic :: Scientific/Engineering :: Information Analysis
Classifier: Programming Language :: Python
Classifier: Programming Language :: Python :: 3.7
Classifier: Programming Language :: Python :: 3.8
Classifier: Programming Language :: Python :: 3.9
Classifier: Programming Language :: Python :: 3.10
Classifier: Programming Language :: Python :: Implementation :: CPython
Classifier: Programming Language :: Python :: Implementation :: PyPy
Classifier: License :: OSI Approved
Classifier: License :: OSI Approved :: Apache Software License
Classifier: Operating System :: OS Independent
Requires-Python: >=3.7
License-File: LICENSE
License-File: AUTHORS.rst
Requires-Dist: numpy >=1.20.0
Requires-Dist: regex >=2021.4.4
Requires-Dist: zeyrek >=0.1.3
Requires-Dist: nltk >=3.8.1
Requires-Dist: pandas >=1.3.4
Requires-Dist: scikit-learn >=1.2.0
Provides-Extra: dev
Requires-Dist: yapf ; extra == 'dev'
Requires-Dist: bumpver ; extra == 'dev'
Requires-Dist: flake8 ; extra == 'dev'
Requires-Dist: coverage ; extra == 'dev'
Requires-Dist: pytest ; extra == 'dev'
